tezaursapi/__init__.py
tezaursapi/exceptions.py
tezaursapi/tezaurs.py
tezaursapi-0.1.0.dist-info/licenses/LICENSE
tezaursapi-0.1.0.dist-info/METADATA
tezaursapi-0.1.0.dist-info/WHEEL
tezaursapi-0.1.0.dist-info/top_level.txt
tezaursapi-0.1.0.dist-info/RECORD
