Metadata-Version: 2.4
Name: tezaursapi
Version: 0.1.0
Summary: Python wrapperis priekš Tezaurs.lv API
Author-email: nrenars <neimanis.renars@gmail.com>
License: MIT License
Project-URL: Homepage, https://github.com/nrenars/tezaurs
Project-URL: Issues, https://github.com/nrenars/tezaurs/issues
Requires-Python: >=3.8
License-File: LICENSE
Requires-Dist: requests
Requires-Dist: xmltodict
Dynamic: license-file
